pty_server/__init__.py
pty_server/async_client.py
pty_server/buffer.py
pty_server/server.py
pty_server-0.3.0.dist-info/LICENSE
pty_server-0.3.0.dist-info/METADATA
pty_server-0.3.0.dist-info/WHEEL
pty_server-0.3.0.dist-info/entry_points.txt
pty_server-0.3.0.dist-info/RECORD
