Metadata-Version: 2.1
Name: pty-server
Version: 0.3.0
Summary: 
Author: Yason Khaburzaniya
Author-email: yason@hey.com
Requires-Python: >=3.10,<4.0
Classifier: Programming Language :: Python :: 3
Classifier: Programming Language :: Python :: 3.10
Classifier: Programming Language :: Python :: 3.11
Classifier: Programming Language :: Python :: 3.12
Requires-Dist: interactive-process (>=0.3.0,<0.4.0)
Requires-Dist: websockets (>=14.1,<15.0)
